MANIFEST.in
README.rst
setup.py
pyDiamondsBackground/Background.py
pyDiamondsBackground/__init__.py
pyDiamondsBackground/strings.py
pyDiamondsBackground.egg-info/PKG-INFO
pyDiamondsBackground.egg-info/SOURCES.txt
pyDiamondsBackground.egg-info/dependency_links.txt
pyDiamondsBackground.egg-info/requires.txt
pyDiamondsBackground.egg-info/top_level.txt
pyDiamondsBackground/models/BackgroundModel.py
pyDiamondsBackground/models/FullBackgroundModel.py
pyDiamondsBackground/models/WhiteNoiseOnlyModel.py
pyDiamondsBackground/models/WhiteNoiseOscillationModel.py
pyDiamondsBackground/models/__init__.py