Metadata-Version: 1.0
Name: pyDiamondsBackground
Version: 1.1.1
Summary: An extension to pyDiamonds, intended for fitting pyDiamondsBackground signals of red giants
Home-page: https://github.com/muma7490/PyDIAMONDS-Background
Author: Marco Muellner
Author-email: muellnermarco@gmail.com
License: UNKNOWN
Platform: UNKNOWN
